NameSpi.py
namespi-1.7.0.dist-info/METADATA
namespi-1.7.0.dist-info/WHEEL
namespi-1.7.0.dist-info/entry_points.txt
namespi-1.7.0.dist-info/top_level.txt
namespi-1.7.0.dist-info/RECORD
