Metadata-Version: 2.1
Name: namespi
Version: 1.7.0
Summary: An OSINT employee/username enumeration tool.
Home-page: https://github.com/waffl3ss/NameSpi
Author: Waffl3ss
Author-email: name@example.com
Classifier: Programming Language :: Python :: 3
Classifier: License :: OSI Approved :: MIT License
Classifier: Operating System :: OS Independent
Requires-Python: >=3.6
Requires-Dist: PyYAML
Requires-Dist: Unidecode
Requires-Dist: pyhunter
Requires-Dist: requests
Requires-Dist: yaspin
